screenot/ScreeNOT.py
screenot/__init__.py
screenot-0.0.2.dist-info/METADATA
screenot-0.0.2.dist-info/WHEEL
screenot-0.0.2.dist-info/licenses/LICENSE
screenot-0.0.2.dist-info/RECORD
