Metadata-Version: 2.4
Name: screenot
Version: 0.0.2
Summary: Code package for ScreeNOT: Exact MSE-Optimal Singular Value Thresholding in Correlated Noise
Project-URL: Homepage, https://github.com/eladromanov/ScreeNOT
Project-URL: Bug Tracker, https://github.com/eladromanov/ScreeNOT/issues
Author-email: Elad Romanov <elad.romanov@gmail.com>
License-File: LICENSE
Classifier: License :: OSI Approved :: MIT License
Classifier: Programming Language :: Python :: 3
